<?xml version="1.0" encoding="utf-8"?>
<!DOCTYPE hibernate-mapping PUBLIC "-//Hibernate/Hibernate Mapping DTD 3.0//EN"
"http://hibernate.sourceforge.net/hibernate-mapping-3.0.dtd">
<!-- 
    Mapping file autogenerated by MyEclipse Persistence Tools
-->
<hibernate-mapping>
    <class name="cn.edu.bnu.land.model.WarmRules" table="WarmRules" lazy="false">
      <id name="id" type="java.lang.Integer">
            <column name="ID"/>
            <generator class="identity"/>
        </id>
       	
       	<property name="createTime" type="java.util.Date">
            <column name="createTime"/>
        </property>
        
        <property name="projectID" type="java.lang.String">
            <column name="projectID" length="30" />
        </property>
        
        <property name="warmTarget" type="java.lang.String">
            <column name="warmTarget" length="20" />
        </property>
        
        <property name="warmContent" type="java.lang.String">
            <column name="warmContent" length="50" />
        </property>     
        
        <property name="endTime" type="java.util.Date">
            <column name="endTime"/>
        </property>
        
        <property name="ruleDescription" type="java.lang.String">
            <column name="ruleDescription" length="200"/>
        </property>
                
        <property name="warmTargetID">
            <column name="warmTargetID"/>
        </property>
        
        <property name="warmContentID">
            <column name="warmContentID"/>
        </property>
        
        <property name="warmCategoryID">
            <column name="warmCategoryID"/>
        </property>
        
        <property name="cycleTime" type="java.lang.Integer">
            <column name="cycleTime"/>
        </property>
        
		<property name="warmCategory" type="java.lang.String">
            <column name="warmCategory" length="30"/>
        </property>
    </class>
</hibernate-mapping>
